powderworld/160worlds.npz
powderworld/__init__.py
powderworld/dists.py
powderworld/envs.py
powderworld/sim.py
powderworld-1.0.0.dist-info/METADATA
powderworld-1.0.0.dist-info/WHEEL
powderworld-1.0.0.dist-info/top_level.txt
powderworld-1.0.0.dist-info/RECORD
